{
    "name": "bc-foundation",
    "username": "ramkumarsg2t",
    "structure": {
        "Layouts": [{
            "name": "Test Affiliate",
            "type": "folder",
            "files": [{
                "name": "affiliate.html",
                "type": "file"
            }]
        },{
            "name": "Affiliate",
            "type": "folder",
            "files": [{
                "name": "affiliate.html",
                "type": "file"
            }]
        }, {
            "name": "Announcement",
            "type": "folder",
            "files": [{
                "name": "detail.html",
                "type": "file"
            }, {
                "name": "list.html",
                "type": "file"
            }]
        }, {
            "name": "Blog",
            "type": "folder",
            "files": [{
                "name": "comment.html",
                "type": "file"
            }, {
                "name": "list.html",
                "type": "file"
            }, {
                "name": "overall.html",
                "type": "file"
            }, {
                "name": "post.html",
                "type": "file"
            }, {
                "name": "postlist.html",
                "type": "file"
            }, {
                "name": "tracklist.html",
                "type": "file"
            }]
        }, {
            "name": "Booking",
            "type": "folder",
            "files": [{
                "name": "detail.html",
                "type": "file"
            }, {
                "name": "list.html",
                "type": "file"
            }]
        }, {
            "name": "Comments",
            "type": "folder",
            "files": [{
                "name": "comments.html",
                "type": "file"
            }]
        }, {
            "name": "CustomerCases",
            "type": "folder",
            "files": [{
                "name": "detail.html",
                "type": "file"
            }, {
                "name": "list.html",
                "type": "file"
            }]
        }, {
            "name": "CustomerOrders",
            "type": "folder",
            "files": [{
                "name": "detail.html",
                "type": "file"
            }, {
                "name": "list.html",
                "type": "file"
            }]
        }, {
            "name": "Faq",
            "type": "folder",
            "files": [{
                "name": "detail.html",
                "type": "file"
            }, {
                "name": "list.html",
                "type": "file"
            }]
        }, {
            "name": "Favorite",
            "type": "folder",
            "files": [{
                "name": "register.html",
                "type": "file"
            }]
        }, {
            "name": "Forum",
            "type": "folder",
            "files": [{
                "name": "forum.html",
                "type": "file"
            }, {
                "name": "post.html",
                "type": "file"
            }, {
                "name": "posts_page.html",
                "type": "file"
            }, {
                "name": "registration_page.html",
                "type": "file"
            }, {
                "name": "topic.html",
                "type": "file"
            }, {
                "name": "topics_page.html",
                "type": "file"
            }]
        }, {
            "name": "Literature",
            "type": "folder",
            "files": [{
                "name": "list.html",
                "type": "file"
            }]
        }, {
            "name": "OnlineShop",
            "type": "folder",
            "files": [{
                "name": "catalogue.html",
                "type": "file"
            }, {
                "name": "gift_voucher-IN.html",
                "type": "file"
            }, {
                "name": "gift_voucher-US.html",
                "type": "file"
            }, {
                "name": "large_product.html",
                "type": "file"
            }, {
                "name": "order_receipt-IN.html",
                "type": "file"
            }, {
                "name": "order_receipt-US.html",
                "type": "file"
            }, {
                "name": "order_registration-IN.html",
                "type": "file"
            }, {
                "name": "order_registration-US.html",
                "type": "file"
            }, {
                "name": "page_content.html",
                "type": "file"
            }, {
                "name": "quote_receipt-IN.html",
                "type": "file"
            }, {
                "name": "quote_receipt-US.html",
                "type": "file"
            }, {
                "name": "quote_registration-IN.html",
                "type": "file"
            }, {
                "name": "quote_registration-US.html",
                "type": "file"
            }, {
                "name": "shopping_cart-IN.html",
                "type": "file"
            }, {
                "name": "shopping_cart-RO.html",
                "type": "file"
            }, {
                "name": "shopping_cart-US.html",
                "type": "file"
            }, {
                "name": "small_product.html",
                "type": "file"
            }, {
                "name": "small_product_backup.html",
                "type": "file"
            }]
        }, {
            "name": "OutboundEmails",
            "type": "folder",
            "files": [{
                "name": "OrderStatusChanged",
                "type": "folder",
                "files": [{
                    "name": "Goods Dispatched.html",
                    "type": "file"
                }, {
                    "name": "Goods Received.html",
                    "type": "file"
                }, {
                    "name": "Purchase - Awaiting Payment.html",
                    "type": "file"
                }, {
                    "name": "Purchase - Payment Received.html",
                    "type": "file"
                }]
            }, {
                "name": "AffiliateProgramDetails.html",
                "type": "file"
            }, {
                "name": "CSF.html",
                "type": "file"
            }, {
                "name": "DoubleOptInEmail.html",
                "type": "file"
            }, {
                "name": "DropShipping.html",
                "type": "file"
            }, {
                "name": "ForumPostSubscriberAlert.html",
                "type": "file"
            }, {
                "name": "ForumTopicSubscriberAlert.html",
                "type": "file"
            }, {
                "name": "GiftVoucherEmail.html",
                "type": "file"
            }, {
                "name": "Invoice.html",
                "type": "file"
            }, {
                "name": "LostPassword.html",
                "type": "file"
            }, {
                "name": "Order.html",
                "type": "file"
            }, {
                "name": "ReferAFriend.html",
                "type": "file"
            }, {
                "name": "SecureZoneDetails.html",
                "type": "file"
            }, {
                "name": "Workflow3rdParty.html",
                "type": "file"
            }, {
                "name": "WorkflowCompletion.html",
                "type": "file"
            }, {
                "name": "WorkflowEscalation.html",
                "type": "file"
            }, {
                "name": "WorkflowNotification.html",
                "type": "file"
            }, {
                "name": "WorkflowRejection.html",
                "type": "file"
            }, {
                "name": "WorkflowReminder.html",
                "type": "file"
            }, {
                "name": "WorkflowTask.html",
                "type": "file"
            }]
        }, {
            "name": "Shipping",
            "type": "folder",
            "files": [{
                "name": "packagelabel.html",
                "type": "file"
            }, {
                "name": "packingslip.html",
                "type": "file"
            }]
        }, {
            "name": "SiteSearch",
            "type": "folder",
            "files": [{
                "name": "site_search.html",
                "type": "file"
            }]
        }, {
            "name": "SystemMessages",
            "type": "folder",
            "files": [{
                "name": "BookingConfirmation-IN.html",
                "type": "file"
            }, {
                "name": "BookingConfirmation-US.html",
                "type": "file"
            }, {
                "name": "BookingVerification-IN.html",
                "type": "file"
            }, {
                "name": "BookingVerification-US.html",
                "type": "file"
            }, {
                "name": "BookingVerificationConfirmForm-IN.html",
                "type": "file"
            }, {
                "name": "BookingVerificationConfirmForm-US.html",
                "type": "file"
            }, {
                "name": "CreditCardPaymentFailure-IN.html",
                "type": "file"
            }, {
                "name": "CreditCardPaymentFailure-US.html",
                "type": "file"
            }, {
                "name": "CustomContentDeleteConfirmation-IN.html",
                "type": "file"
            }, {
                "name": "CustomContentDeleteConfirmation-US.html",
                "type": "file"
            }, {
                "name": "CustomContentInputFormConfirmation-IN.html",
                "type": "file"
            }, {
                "name": "CustomContentInputFormConfirmation-US.html",
                "type": "file"
            }, {
                "name": "Error401-IN.html",
                "type": "file"
            }, {
                "name": "Error401-US.html",
                "type": "file"
            }, {
                "name": "Error404-IN.html",
                "type": "file"
            }, {
                "name": "Error404-US.html",
                "type": "file"
            }, {
                "name": "FavoritesConfirmation-IN.html",
                "type": "file"
            }, {
                "name": "FavoritesConfirmation-US.html",
                "type": "file"
            }, {
                "name": "FormConfirmation-IN.html",
                "type": "file"
            }, {
                "name": "FormConfirmation-US.html",
                "type": "file"
            }, {
                "name": "General-IN.html",
                "type": "file"
            }, {
                "name": "General-US.html",
                "type": "file"
            }, {
                "name": "NewsletterSubscribeConfirm-IN.html",
                "type": "file"
            }, {
                "name": "NewsletterSubscribeConfirm-US.html",
                "type": "file"
            }, {
                "name": "NewsletterUnsubscribeConfirm-IN.html",
                "type": "file"
            }, {
                "name": "NewsletterUnsubscribeConfirm-US.html",
                "type": "file"
            }, {
                "name": "PasswordReset-IN.html",
                "type": "file"
            }, {
                "name": "PasswordReset-US.html",
                "type": "file"
            }, {
                "name": "PasswordResetSuccess-IN.html",
                "type": "file"
            }, {
                "name": "PasswordResetSuccess-US.html",
                "type": "file"
            }, {
                "name": "PasswordRetrieve-IN.html",
                "type": "file"
            }, {
                "name": "PasswordRetrieve-US.html",
                "type": "file"
            }, {
                "name": "PasswordRetrieveRequest-IN.html",
                "type": "file"
            }, {
                "name": "PasswordRetrieveRequest-US.html",
                "type": "file"
            }, {
                "name": "RatingConfirmation-IN.html",
                "type": "file"
            }, {
                "name": "RatingConfirmation-US.html",
                "type": "file"
            }, {
                "name": "RatingDenied-IN.html",
                "type": "file"
            }, {
                "name": "RatingDenied-US.html",
                "type": "file"
            }, {
                "name": "ReferAFriendConfirmation-IN.html",
                "type": "file"
            }, {
                "name": "ReferAFriendConfirmation-US.html",
                "type": "file"
            }, {
                "name": "SecureZoneAccessDenied-IN.html",
                "type": "file"
            }, {
                "name": "SecureZoneAccessDenied-US.html",
                "type": "file"
            }, {
                "name": "SecureZoneAccessExpired-IN.html",
                "type": "file"
            }, {
                "name": "SecureZoneAccessExpired-US.html",
                "type": "file"
            }, {
                "name": "SecureZoneLogOut-IN.html",
                "type": "file"
            }, {
                "name": "SecureZoneLogOut-US.html",
                "type": "file"
            }, {
                "name": "SubscribeConfirmForm-IN.html",
                "type": "file"
            }, {
                "name": "SubscribeConfirmForm-US.html",
                "type": "file"
            }, {
                "name": "UnsubscribeConfirmForm-IN.html",
                "type": "file"
            }, {
                "name": "UnsubscribeConfirmForm-US.html",
                "type": "file"
            }, {
                "name": "UpdateDetailsConfirmation-IN.html",
                "type": "file"
            }, {
                "name": "UpdateDetailsConfirmation-US.html",
                "type": "file"
            }]
        }, {
            "name": "WebApps",
            "type": "folder"
        }],
        "core": [
            {
                "name" : "Scripts",
                "type" : "folder",
                "files" : [
                    {
                        "name" : "footScripts.js",
                        "type" : "file"
                    },
                    {
                        "name" : "headScripts.js",
                        "type" : "file"
                    },
                    {
                        "name" : "min",
                        "type" : "folder",
                        "files" : [
                            {
                                "name" : "footScripts.min.js",
                                "type" : "file"
                            },
                            {
                                "name" : "headScripts.min.js",
                                "type" : "file"
                            }
                        ]
                    }
                ]
            }
        ],
        "template": []
    }
}
